easymq/__init__.py
easymq/listener.py
easymq/mq.py
easymq-2.1.0.dist-info/LICENSE
easymq-2.1.0.dist-info/METADATA
easymq-2.1.0.dist-info/WHEEL
easymq-2.1.0.dist-info/top_level.txt
easymq-2.1.0.dist-info/RECORD
