Metadata-Version: 2.1
Name: easymq
Version: 2.1.0
Summary: easy to connect activemq
Home-page: https://github.com/localhost-sys/easymq
Author: unknown-admin
Author-email: niushuaibing@foxmail.com
Maintainer: eric
Maintainer-email: niushuaibing@foxmail.com
License: apache
Platform: all
Classifier: Development Status :: 5 - Production/Stable
Classifier: Intended Audience :: Developers
Classifier: License :: OSI Approved :: Apache Software License
Classifier: Programming Language :: Python :: 3
Requires-Dist: stomp.py
Requires-Dist: docopt
